rpi_app_framework/__init__.py
rpi_app_framework/device_manager.py
rpi_app_framework/hardware.py
rpi_app_framework/led_simple.py
rpi_app_framework/microdot_manager.py
rpi_app_framework/motor_driver_tb6612.py
rpi_app_framework/rpi_app.py
rpi_app_framework/wifi_manager.py
rpi_app_framework-0.1.2.dist-info/licenses/LICENSE
rpi_app_framework-0.1.2.dist-info/METADATA
rpi_app_framework-0.1.2.dist-info/WHEEL
rpi_app_framework-0.1.2.dist-info/top_level.txt
rpi_app_framework-0.1.2.dist-info/RECORD
