Metadata-Version: 2.4
Name: rpi-app-framework
Version: 0.1.2
Summary: A Python framework for building applications on all Raspberry Pi versions, including Pico.
Home-page: https://github.com/yourusername/rpi-app-framework
Author: Your Name
Author-email: John Singer <john@singerlinks.com>
License-Expression: MIT
Project-URL: Homepage, https://github.com/jsinger0420/rpi-app-framework
Project-URL: Repository, https://github.com/jsinger0420/rpi-app-framework.git
Project-URL: Documentation, https://github.com/jsinger0420/rpi-app-framework/wiki
Project-URL: Bug Tracker, https://github.com/jsinger0420/rpi-app-framework/issues
Keywords: raspberry-pi,pico,framework,app-development,iot
Classifier: Development Status :: 3 - Alpha
Classifier: Intended Audience :: Developers
Classifier: Operating System :: POSIX :: Linux
Classifier: Programming Language :: Python :: 3
Classifier: Programming Language :: Python :: 3.7
Classifier: Programming Language :: Python :: 3.8
Classifier: Programming Language :: Python :: 3.9
Classifier: Programming Language :: Python :: 3.10
Classifier: Programming Language :: Python :: 3.11
Classifier: Topic :: Software Development :: Libraries :: Application Frameworks
Classifier: Topic :: System :: Hardware
Requires-Python: >=3.6
License-File: LICENSE
Provides-Extra: pi
Requires-Dist: RPi.GPIO>=0.7.0; extra == "pi"
Provides-Extra: test
Requires-Dist: pytest>=7.0; extra == "test"
Requires-Dist: pytest-cov>=4.0; extra == "test"
Provides-Extra: dev
Requires-Dist: black>=23.0; extra == "dev"
Requires-Dist: isort>=5.0; extra == "dev"
Requires-Dist: flake8>=6.0; extra == "dev"
Dynamic: author
Dynamic: home-page
Dynamic: license-file
Dynamic: requires-python
